pywxdll/__init__.py
pywxdll/pywxdll.py
pywxdll/pywxdll_json.py
pywxdll-0.2.4.dist-info/LICENSE
pywxdll-0.2.4.dist-info/METADATA
pywxdll-0.2.4.dist-info/WHEEL
pywxdll-0.2.4.dist-info/top_level.txt
pywxdll-0.2.4.dist-info/RECORD
