Metadata-Version: 2.1
Name: pywxdll
Version: 0.2.4
Summary: A Python package for wechat robot, basing on dll hook.
Home-page: https://github.com/HenryXiaoYang/pywxdll
Author: HenryXiaoYang
Author-email: henryyang666@hotmal.com
License: MIT
Platform: UNKNOWN
Classifier: License :: OSI Approved :: MIT License
Classifier: Programming Language :: Python
Classifier: Programming Language :: Python :: 3
Classifier: Programming Language :: Python :: 3.6
Classifier: Programming Language :: Python :: Implementation :: CPython
Classifier: Programming Language :: Python :: Implementation :: PyPy
Requires-Python: >=3.6.0
License-File: LICENSE
Requires-Dist: websocket-client
Requires-Dist: requests
